{
  "1536356": {
    "yes": 0.9995,
    "no": 0.0005,
    "volume": 5026213.837552995,
    "question": "Will FC Barcelona win on 2026-03-22?",
    "updated": "2026-03-22T12:43:38.154212"
  },
  "1543344": {
    "yes": 0.0005,
    "no": 0.9995,
    "volume": 4937284.707871003,
    "question": "Will Newcastle United FC win on 2026-03-22?",
    "updated": "2026-03-22T11:45:29.195730"
  },
  "561986": {
    "yes": 0.0045,
    "no": 0.9955,
    "volume": 4277670.82610301,
    "question": "Will Byron Donalds win the 2028 Republican presidential nomination?",
    "updated": "2026-03-22T12:43:38.154244"
  },
  "1543379": {
    "yes": 0.0005,
    "no": 0.9995,
    "volume": 3961214.411919003,
    "question": "Will Bologna FC 1909 win on 2026-03-22?",
    "updated": "2026-03-22T12:43:38.154250"
  },
  "1674395": {
    "yes": 0.0005,
    "no": 0.9995,
    "volume": 4336279.561065982,
    "question": "LoL: G2 Esports vs Bilibili Gaming (BO5) - First Stand Playoffs",
    "updated": "2026-03-22T12:43:38.154237"
  },
  "contested_1665981_2026-03-22": {
    "flagged": true
  },
  "1665981": {
    "yes": 0.505,
    "no": 0.495,
    "volume": 3620911.836313013,
    "question": "Texas Tech Red Raiders vs. Alabama Crimson Tide",
    "updated": "2026-03-22T12:43:38.154283"
  },
  "948046": {
    "yes": 0.0005,
    "no": 0.9995,
    "volume": 3089255.840000001,
    "question": "Will LMP \u2013 Hungary\u2019s Green Party (LMP) win the most seats in the next Hungarian parliamentary electi",
    "updated": "2026-03-22T12:43:38.154291"
  },
  "1484949": {
    "yes": 0.0105,
    "no": 0.9895,
    "volume": 2555464.8081919993,
    "question": "Netanyahu out by March 31?",
    "updated": "2026-03-22T12:43:38.154296"
  },
  "559680": {
    "yes": 0.0095,
    "no": 0.9905,
    "volume": 2331742.051400002,
    "question": "Will Phil Murphy win the 2028 Democratic presidential nomination?",
    "updated": "2026-03-22T12:43:38.154301"
  },
  "1466015": {
    "yes": 0.085,
    "no": 0.915,
    "volume": 2070169.0718599993,
    "question": "US x Iran ceasefire by March 31?",
    "updated": "2026-03-22T12:43:38.154305"
  },
  "1674397": {
    "yes": 0.0005,
    "no": 0.9995,
    "volume": 2069729.7069750014,
    "question": "LoL: G2 Esports vs Bilibili Gaming - Game 2 Winner",
    "updated": "2026-03-22T12:43:38.154309"
  },
  "561992": {
    "yes": 0.0085,
    "no": 0.9915,
    "volume": 1967312.822027001,
    "question": "Will Katie Britt win the 2028 Republican presidential nomination?",
    "updated": "2026-03-22T12:43:38.154314"
  },
  "677397": {
    "yes": 0.99,
    "no": 0.01,
    "volume": 1775246.4166320013,
    "question": "Will Israel launch a major ground offensive in Lebanon by March 31?",
    "updated": "2026-03-22T12:43:38.154319"
  },
  "1674396": {
    "yes": 0.9995,
    "no": 0.0005,
    "volume": 1466857.4276609977,
    "question": "LoL: G2 Esports vs Bilibili Gaming - Game 1 Winner",
    "updated": "2026-03-22T12:43:38.154335"
  },
  "1543355": {
    "yes": 0.0005,
    "no": 0.9995,
    "volume": 1522648.8904140021,
    "question": "Will Tottenham Hotspur FC win on 2026-03-22?",
    "updated": "2026-03-22T12:43:38.154327"
  },
  "561989": {
    "yes": 0.0105,
    "no": 0.9895,
    "volume": 1332613.2401000024,
    "question": "Will Ted Cruz win the 2028 Republican presidential nomination?",
    "updated": "2026-03-22T12:43:38.154340"
  },
  "1543351": {
    "yes": 0.9995,
    "no": 0.0005,
    "volume": 1302603.2268319966,
    "question": "Will Aston Villa FC win on 2026-03-22?",
    "updated": "2026-03-22T12:43:38.154356"
  },
  "1667148": {
    "yes": 0.0005,
    "no": 0.9995,
    "volume": 1154813.7567920005,
    "question": "Counter-Strike: TYLOO vs Team Falcons (BO3) - BLAST Open Rotterdam Group A",
    "updated": "2026-03-22T12:43:38.154369"
  },
  "559690": {
    "yes": 0.0085,
    "no": 0.9915,
    "volume": 1195305.3379450007,
    "question": "Will Kim Kardashian win the 2028 Democratic presidential nomination?",
    "updated": "2026-03-22T12:43:38.154365"
  },
  "contested_1668985_2026-03-22": {
    "flagged": true
  },
  "1668985": {
    "yes": 0.355,
    "no": 0.645,
    "volume": 1117473.5633199995,
    "question": "UCLA Bruins vs. Connecticut Huskies",
    "updated": "2026-03-22T12:43:38.154386"
  },
  "958442": {
    "yes": 0.0185,
    "no": 0.9815,
    "volume": 1074871.6478870008,
    "question": "Will the Iranian regime fall by March 31?",
    "updated": "2026-03-22T12:43:38.154390"
  },
  "1543357": {
    "yes": 0.9995,
    "no": 0.0005,
    "volume": 1262800.1180389998,
    "question": "Will Nottingham Forest FC win on 2026-03-22?",
    "updated": "2026-03-22T12:43:38.154361"
  },
  "1473040": {
    "yes": 0.0025,
    "no": 0.9975,
    "volume": 860365.4859970008,
    "question": "Will Bitcoin reach $150,000 in March?",
    "updated": "2026-03-22T12:43:38.154415"
  },
  "559687": {
    "yes": 0.0095,
    "no": 0.9905,
    "volume": 878366.810953999,
    "question": "Will Oprah Winfrey win the 2028 Democratic presidential nomination?",
    "updated": "2026-03-22T12:43:38.154411"
  },
  "559683": {
    "yes": 0.0075,
    "no": 0.9925,
    "volume": 810770.111222,
    "question": "Will George Clooney win the 2028 Democratic presidential nomination?",
    "updated": "2026-03-22T12:43:38.154430"
  },
  "contested_1473072_2026-03-22": {
    "flagged": true
  },
  "1473072": {
    "yes": 0.525,
    "no": 0.475,
    "volume": 820545.3960740007,
    "question": "Will Bitcoin dip to $65,000 in March?",
    "updated": "2026-03-22T12:43:38.154422"
  },
  "1569627": {
    "yes": 0.275,
    "no": 0.725,
    "volume": 816791.0581590006,
    "question": "US x Iran ceasefire by April 15?",
    "updated": "2026-03-22T12:43:38.154426"
  },
  "1666995": {
    "yes": 0.335,
    "no": 0.665,
    "volume": 1126211.7880949995,
    "question": "Counter-Strike: NRG vs FURIA (BO3) - BLAST Open Rotterdam Group A",
    "updated": "2026-03-22T12:43:38.154377"
  },
  "1674399": {
    "yes": 0.0005,
    "no": 0.9995,
    "volume": 996648.2586730004,
    "question": "LoL: G2 Esports vs Bilibili Gaming - Game 3 Winner",
    "updated": "2026-03-22T12:43:38.154407"
  },
  "1607251": {
    "yes": 0.0005,
    "no": 0.9995,
    "volume": 783556.7230589997,
    "question": "Will MrBeast's next video get between 30 and 35 million views on day 1?",
    "updated": "2026-03-22T12:43:38.154434"
  },
  "559678": {
    "yes": 0.0125,
    "no": 0.9875,
    "volume": 749592.6681080003,
    "question": "Will Liz Cheney win the 2028 Democratic presidential nomination?",
    "updated": "2026-03-22T12:43:38.154449"
  },
  "1666743": {
    "yes": 0.145,
    "no": 0.855,
    "volume": 756737.4472910002,
    "question": "Utah State Aggies vs. Arizona Wildcats",
    "updated": "2026-03-22T12:43:38.154438"
  },
  "contested_1666732_2026-03-22": {
    "flagged": true
  },
  "1666732": {
    "yes": 0.505,
    "no": 0.495,
    "volume": 1051960.9674269992,
    "question": "Tennessee Volunteers vs. Virginia Cavaliers",
    "updated": "2026-03-22T12:43:38.154403"
  },
  "561982": {
    "yes": 0.0085,
    "no": 0.9915,
    "volume": 543807.8185030002,
    "question": "Will Sarah Huckabee Sanders win the 2028 Republican presidential nomination?",
    "updated": "2026-03-22T12:43:38.154504"
  },
  "669661": {
    "yes": 0.0125,
    "no": 0.9875,
    "volume": 652397.9032700001,
    "question": "Will the Fed decrease interest rates by 25 bps after the April 2026 meeting?",
    "updated": "2026-03-22T12:43:38.154469"
  },
  "669660": {
    "yes": 0.0045,
    "no": 0.9955,
    "volume": 1071246.3658350003,
    "question": "Will the Fed decrease interest rates by 50+ bps after the April 2026 meeting?",
    "updated": "2026-03-22T12:43:38.154394"
  },
  "1607253": {
    "yes": 0.0005,
    "no": 0.9995,
    "volume": 677728.3612380001,
    "question": "Will MrBeast's next video get between 40 and 45 million views on day 1?",
    "updated": "2026-03-22T12:43:38.154466"
  },
  "contested_1606817_2026-03-22": {
    "flagged": true
  },
  "1606817": {
    "yes": 0.595,
    "no": 0.405,
    "volume": 730875.8923130013,
    "question": "Raptors vs. Suns",
    "updated": "2026-03-22T12:43:38.154455"
  },
  "1598798": {
    "yes": 0.9995,
    "no": 0.0005,
    "volume": 532619.2915439998,
    "question": "Will the price of Bitcoin be above $66,000 on March 22?",
    "updated": "2026-03-22T12:43:38.154523"
  },
  "561994": {
    "yes": 0.0075,
    "no": 0.9925,
    "volume": 617250.363854,
    "question": "Will Kristi Noem win the 2028 Republican presidential nomination?",
    "updated": "2026-03-22T12:43:38.154490"
  },
  "1668647": {
    "yes": 0.165,
    "no": 0.835,
    "volume": 630338.9401349997,
    "question": "Iowa Hawkeyes vs. Florida Gators",
    "updated": "2026-03-22T12:43:38.154480"
  },
  "559688": {
    "yes": 0.0085,
    "no": 0.9915,
    "volume": 725562.7952649998,
    "question": "Will Andrew Yang win the 2028 Democratic presidential nomination?",
    "updated": "2026-03-22T12:43:38.154458"
  },
  "559677": {
    "yes": 0.0075,
    "no": 0.9925,
    "volume": 627028.7480700003,
    "question": "Will Hillary Clinton win the 2028 Democratic presidential nomination?",
    "updated": "2026-03-22T12:43:38.154486"
  },
  "1473075": {
    "yes": 0.0635,
    "no": 0.9365,
    "volume": 628080.8591209997,
    "question": "Will Bitcoin dip to $55,000 in March?",
    "updated": "2026-03-22T12:43:38.154483"
  },
  "669663": {
    "yes": 0.0355,
    "no": 0.9645,
    "volume": 578132.5213260005,
    "question": "Will the Fed increase interest rates by 25+ bps after the April 2026 meeting?",
    "updated": "2026-03-22T12:43:38.154497"
  },
  "1536362": {
    "yes": 0.745,
    "no": 0.255,
    "volume": 680044.4738689997,
    "question": "Will RC Celta de Vigo win on 2026-03-22?",
    "updated": "2026-03-22T12:43:38.154462"
  },
  "559681": {
    "yes": 0.0105,
    "no": 0.9895,
    "volume": 565672.440091,
    "question": "Will LeBron James win the 2028 Democratic presidential nomination?",
    "updated": "2026-03-22T12:43:38.154501"
  },
  "1677887": {
    "yes": 0.335,
    "no": 0.665,
    "volume": 580821.2967089999,
    "question": "Counter-Strike: Liquid vs TheMongolz (BO3) - BLAST Open Rotterdam Group B",
    "updated": "2026-03-22T12:43:38.154494"
  },
  "566146": {
    "yes": 0.0355,
    "no": 0.9645,
    "volume": 536102.3461060002,
    "question": "Will Atletico Madrid win the 2025\u201326 Champions League?",
    "updated": "2026-03-22T12:43:38.154512"
  },
  "contested_1423643_2026-03-22": {
    "flagged": true
  },
  "1423643": {
    "yes": 0.405,
    "no": 0.595,
    "volume": 1315023.0290289994,
    "question": "Will Arsenal FC win on 2026-03-22?",
    "updated": "2026-03-22T12:43:38.154351"
  },
  "1543360": {
    "yes": 0.9995,
    "no": 0.0005,
    "volume": 543642.1262000002,
    "question": "Will Como 1907 win on 2026-03-22?",
    "updated": "2026-03-22T12:43:38.154508"
  },
  "1162940": {
    "yes": 0.185,
    "no": 0.815,
    "volume": 528521.8851390004,
    "question": "US forces enter Iran by March 31?",
    "updated": "2026-03-22T12:43:38.154534"
  },
  "1665984": {
    "yes": 0.325,
    "no": 0.675,
    "volume": 531503.7676330003,
    "question": "Kentucky Wildcats vs. Iowa State Cyclones",
    "updated": "2026-03-22T12:43:38.154526"
  },
  "1130015": {
    "yes": 0.0685,
    "no": 0.9315,
    "volume": 515585.64022700005,
    "question": "Will the Liberal Democratic Party of Russia (LDPR) gain the most seats in the next Russian parliamen",
    "updated": "2026-03-22T12:43:38.154545"
  },
  "558941": {
    "yes": 0.032,
    "no": 0.968,
    "volume": 501755.7691690003,
    "question": "Will Netherlands win the 2026 FIFA World Cup?",
    "updated": "2026-03-22T12:43:38.154559"
  },
  "contested_1427879_2026-03-22": {
    "flagged": true
  },
  "1427879": {
    "yes": 0.575,
    "no": 0.425,
    "volume": 505708.17133700004,
    "question": "Hurricanes vs. Penguins",
    "updated": "2026-03-22T12:43:38.154552"
  },
  "1374263": {
    "yes": 0.9425,
    "no": 0.0575,
    "volume": 504682.33800300007,
    "question": "Will annual inflation increase by \u22652.8% in March?",
    "updated": "2026-03-22T12:43:38.154555"
  },
  "1543367": {
    "yes": 0.9995,
    "no": 0.0005,
    "volume": 531101.1275940001,
    "question": "Will Atalanta BC win on 2026-03-22?",
    "updated": "2026-03-22T12:43:38.154530"
  },
  "898424": {
    "yes": 0.0045,
    "no": 0.9955,
    "volume": 490417.6813580001,
    "question": "Will Franco Colapinto be the 2026 F1 Drivers' Champion?",
    "updated": "2026-03-22T12:43:38.154569"
  },
  "553851": {
    "yes": 0.063,
    "no": 0.937,
    "volume": 476461.73674500006,
    "question": "Will the Buffalo Sabres win the 2026 NHL Stanley Cup?",
    "updated": "2026-03-22T12:43:38.154576"
  },
  "1607252": {
    "yes": 0.9985,
    "no": 0.0015,
    "volume": 517469.01534899994,
    "question": "Will MrBeast's next video get between 35 and 40 million views on day 1?",
    "updated": "2026-03-22T12:43:38.154541"
  },
  "1543346": {
    "yes": 0.0005,
    "no": 0.9995,
    "volume": 460795.99780499976,
    "question": "Will Newcastle United FC vs. Sunderland AFC end in a draw?",
    "updated": "2026-03-22T11:45:29.195917"
  },
  "1507751": {
    "yes": 0.115,
    "no": 0.885,
    "volume": 384581.2617010002,
    "question": "Will the Iranian regime fall by April 30?",
    "updated": "2026-03-22T12:43:38.154685"
  },
  "1607250": {
    "yes": 0.0005,
    "no": 0.9995,
    "volume": 458540.613044,
    "question": "Will MrBeast's next video get between 25 and 30 million views on day 1?",
    "updated": "2026-03-22T12:43:38.154583"
  },
  "1606809": {
    "yes": 0.315,
    "no": 0.685,
    "volume": 518844.76837400004,
    "question": "Nets vs. Kings",
    "updated": "2026-03-22T12:43:38.154538"
  },
  "658949": {
    "yes": 0.036,
    "no": 0.964,
    "volume": 418775.09664100007,
    "question": "Will Iowa State win the 2026 NCAA Tournament?",
    "updated": "2026-03-22T12:43:38.154619"
  },
  "1598804": {
    "yes": 0.0005,
    "no": 0.9995,
    "volume": 422532.4495029997,
    "question": "Will the price of Bitcoin be above $72,000 on March 22?",
    "updated": "2026-03-22T12:43:38.154616"
  },
  "558963": {
    "yes": 0.016,
    "no": 0.984,
    "volume": 418753.50672299985,
    "question": "Will Morocco win the 2026 FIFA World Cup?",
    "updated": "2026-03-22T12:43:38.154623"
  },
  "1547838": {
    "yes": 0.9995,
    "no": 0.0005,
    "volume": 434874.1721020002,
    "question": "Newcastle United FC vs. Sunderland AFC: O/U 2.5",
    "updated": "2026-03-22T12:43:38.154598"
  },
  "1500768": {
    "yes": 0.0015,
    "no": 0.9985,
    "volume": 462570.5470000001,
    "question": "Will Scott Bessent be confirmed as Fed Chair?",
    "updated": "2026-03-22T12:43:38.154580"
  },
  "1598793": {
    "yes": 0.9995,
    "no": 0.0005,
    "volume": 401286.30101199984,
    "question": "Will the price of Bitcoin be above $64,000 on March 22?",
    "updated": "2026-03-22T12:43:38.154652"
  },
  "567621": {
    "yes": 0.108,
    "no": 0.892,
    "volume": 418326.7256600001,
    "question": "Will China invade Taiwan by end of 2026?",
    "updated": "2026-03-22T12:43:38.154626"
  },
  "contested_1681788_2026-03-22": {
    "flagged": true
  },
  "1681788": {
    "yes": 0.475,
    "no": 0.525,
    "volume": 417413.1264900001,
    "question": "Nets vs. Kings: O/U 219.5",
    "updated": "2026-03-22T12:43:38.154633"
  },
  "1543348": {
    "yes": 0.9995,
    "no": 0.0005,
    "volume": 410918.96962300054,
    "question": "Will Sunderland AFC win on 2026-03-22?",
    "updated": "2026-03-22T11:45:29.195946"
  },
  "1500755": {
    "yes": 0.0215,
    "no": 0.9785,
    "volume": 400931.837335,
    "question": "Will Judy Shelton be confirmed as Fed Chair?",
    "updated": "2026-03-22T12:43:38.154655"
  },
  "contested_1677311_2026-03-22": {
    "flagged": true
  },
  "1677311": {
    "yes": 0.515,
    "no": 0.485,
    "volume": 411425.8896190001,
    "question": "Spread: Celtics (-9.5)",
    "updated": "2026-03-22T12:43:38.154648"
  },
  "contested_1677952_2026-03-22": {
    "flagged": true
  },
  "1677952": {
    "yes": 0.555,
    "no": 0.445,
    "volume": 396926.712508,
    "question": "Spread: Knicks (-19.5)",
    "updated": "2026-03-22T12:43:38.154662"
  },
  "568666": {
    "yes": 0.025,
    "no": 0.975,
    "volume": 385120.9303920001,
    "question": "Will Matt Fitzpatrick win the 2026 Masters tournament?",
    "updated": "2026-03-22T12:43:38.154681"
  },
  "1349162": {
    "yes": 0.0515,
    "no": 0.9485,
    "volume": 389302.13444000005,
    "question": "Will Orlando City SC win the 2026 MLS Cup?",
    "updated": "2026-03-22T12:43:38.154670"
  },
  "898426": {
    "yes": 0.0045,
    "no": 0.9955,
    "volume": 392295.859103,
    "question": "Will Arvid Lindblad be the 2026 F1 Drivers' Champion?",
    "updated": "2026-03-22T12:43:38.154666"
  },
  "1105754": {
    "yes": 0.0005,
    "no": 0.9995,
    "volume": 431725.1499999999,
    "question": "Will Richard Grenell be the leader of Venezuela end of 2026?",
    "updated": "2026-03-22T12:43:38.154605"
  },
  "559663": {
    "yes": 0.0275,
    "no": 0.9725,
    "volume": 369779.6974569999,
    "question": "Will J.B. Pritzker win the 2028 Democratic presidential nomination?",
    "updated": "2026-03-22T12:43:38.154701"
  },
  "1547853": {
    "yes": 0.9995,
    "no": 0.0005,
    "volume": 437897.456402,
    "question": "1. FSV Mainz 05 vs. Eintracht Frankfurt: O/U 2.5",
    "updated": "2026-03-22T12:43:38.154595"
  },
  "1466575": {
    "yes": 0.12,
    "no": 0.88,
    "volume": 374841.894525,
    "question": "Trump announces end of military operations against Iran by March 31st?",
    "updated": "2026-03-22T12:43:38.154697"
  },
  "561248": {
    "yes": 0.0105,
    "no": 0.9895,
    "volume": 386496.943569,
    "question": "Will Vivek Ramaswamy win the 2028 US Presidential Election?",
    "updated": "2026-03-22T12:43:38.154678"
  },
  "1536359": {
    "yes": 0.0005,
    "no": 0.9995,
    "volume": 388308.8231749997,
    "question": "Will Rayo Vallecano de Madrid win on 2026-03-22?",
    "updated": "2026-03-22T12:43:38.154674"
  },
  "1598799": {
    "yes": 0.9995,
    "no": 0.0005,
    "volume": 432883.84463900025,
    "question": "Will the price of Bitcoin be above $68,000 on March 22?",
    "updated": "2026-03-22T12:43:38.154601"
  },
  "contested_1677317_2026-03-22": {
    "flagged": true
  },
  "1677317": {
    "yes": 0.48,
    "no": 0.52,
    "volume": 379906.725681,
    "question": "Raptors vs. Suns: O/U 220.5",
    "updated": "2026-03-22T12:43:38.154691"
  },
  "658945": {
    "yes": 0.029,
    "no": 0.971,
    "volume": 379695.2147730001,
    "question": "Will Connecticut win the 2026 NCAA Tournament?",
    "updated": "2026-03-22T11:45:29.195986"
  },
  "958443": {
    "yes": 0.235,
    "no": 0.765,
    "volume": 416947.54327400035,
    "question": "Will the Iranian regime fall by June 30?",
    "updated": "2026-03-22T12:43:38.154640"
  },
  "1598805": {
    "yes": 0.0005,
    "no": 0.9995,
    "volume": 367081.5552119999,
    "question": "Will the price of Bitcoin be above $74,000 on March 22?",
    "updated": "2026-03-22T11:45:29.195990"
  },
  "898428": {
    "yes": 0.0045,
    "no": 0.9955,
    "volume": 364344.9061779999,
    "question": "Will Carlos Sainz Jr. be the 2026 F1 Drivers' Champion?",
    "updated": "2026-03-22T12:43:38.154704"
  },
  "669662": {
    "yes": 0.9465,
    "no": 0.0535,
    "volume": 360779.8652009998,
    "question": "Will there be no change in Fed interest rates after the April 2026 meeting?",
    "updated": "2026-03-22T11:45:29.195995"
  },
  "559665": {
    "yes": 0.0115,
    "no": 0.9885,
    "volume": 359148.9668810007,
    "question": "Will Cory Booker win the 2028 Democratic presidential nomination?",
    "updated": "2026-03-22T11:45:29.195997"
  },
  "898420": {
    "yes": 0.0045,
    "no": 0.9955,
    "volume": 351051.4460170001,
    "question": "Will Oliver Bearman be the 2026 F1 Drivers' Champion?",
    "updated": "2026-03-22T11:45:29.195999"
  },
  "1547727": {
    "yes": 0.9995,
    "no": 0.0005,
    "volume": 417368.00222399965,
    "question": "Tottenham Hotspur FC vs. Nottingham Forest FC: O/U 2.5",
    "updated": "2026-03-22T12:43:38.154637"
  },
  "1666996": {
    "yes": 0.9995,
    "no": 0.0005,
    "volume": 377799.0114459999,
    "question": "Counter-Strike: NRG vs FURIA - Map 1 Winner",
    "updated": "2026-03-22T12:43:38.154694"
  },
  "1516204": {
    "yes": 0.0105,
    "no": 0.9895,
    "volume": 341350.2609699999,
    "question": "Will Crude Oil (CL) hit (HIGH) $200 by end of March?",
    "updated": "2026-03-22T11:45:29.196005"
  },
  "1543385": {
    "yes": 0.985,
    "no": 0.015,
    "volume": 338564.66801400034,
    "question": "Will SS Lazio win on 2026-03-22?",
    "updated": "2026-03-22T11:45:29.196007"
  },
  "1547920": {
    "yes": 0.9995,
    "no": 0.0005,
    "volume": 335405.121216,
    "question": "Olympique Lyonnais vs. AS Monaco FC: O/U 2.5",
    "updated": "2026-03-22T11:45:29.196010"
  },
  "1543381": {
    "yes": 0.735,
    "no": 0.265,
    "volume": 1546032.4865630006,
    "question": "Will Stade Rennais FC 1901 win on 2026-03-22?",
    "updated": "2026-03-22T12:43:38.154323"
  },
  "1668974": {
    "yes": 0.185,
    "no": 0.815,
    "volume": 1495613.3457819994,
    "question": "Miami Hurricanes vs. Purdue Boilermakers",
    "updated": "2026-03-22T12:43:38.154331"
  },
  "1674401": {
    "yes": 0.0005,
    "no": 0.9995,
    "volume": 1152621.3653739998,
    "question": "LoL: G2 Esports vs Bilibili Gaming - Game 4 Winner",
    "updated": "2026-03-22T12:43:38.154373"
  },
  "contested_1427862_2026-03-22": {
    "flagged": true
  },
  "1427862": {
    "yes": 0.645,
    "no": 0.355,
    "volume": 750564.6062519997,
    "question": "Jets vs. Rangers",
    "updated": "2026-03-22T12:43:38.154444"
  },
  "contested_1427875_2026-03-22": {
    "flagged": true
  },
  "1427875": {
    "yes": 0.44,
    "no": 0.56,
    "volume": 632293.1961240002,
    "question": "Avalanche vs. Capitals: O/U 6.5",
    "updated": "2026-03-22T12:43:38.154476"
  },
  "contested_1669736_2026-03-22": {
    "flagged": true
  },
  "1669736": {
    "yes": 0.55,
    "no": 0.45,
    "volume": 535922.7818780002,
    "question": "Spread: Purdue Boilermakers (-7.5)",
    "updated": "2026-03-22T12:43:38.154519"
  },
  "contested_1547894_2026-03-22": {
    "flagged": true
  },
  "1547894": {
    "yes": 0.42,
    "no": 0.58,
    "volume": 491304.8693749998,
    "question": "Olympique de Marseille vs. Lille OSC: O/U 2.5",
    "updated": "2026-03-22T12:43:38.154565"
  },
  "666860": {
    "yes": 0.0045,
    "no": 0.9955,
    "volume": 476914.41321200004,
    "question": "Trump out as President by March 31?",
    "updated": "2026-03-22T12:43:38.154572"
  },
  "contested_1427870_2026-03-22": {
    "flagged": true
  },
  "1427870": {
    "yes": 0.605,
    "no": 0.395,
    "volume": 455628.01738900004,
    "question": "Avalanche vs. Capitals",
    "updated": "2026-03-22T12:43:38.154590"
  },
  "1543366": {
    "yes": 0.9995,
    "no": 0.0005,
    "volume": 429928.69794699986,
    "question": "Will 1. FSV Mainz 05 win on 2026-03-22?",
    "updated": "2026-03-22T12:43:38.154608"
  },
  "559692": {
    "yes": 0.0075,
    "no": 0.9925,
    "volume": 423838.470823,
    "question": "Will Jasmine Crockett win the 2028 Democratic presidential nomination?",
    "updated": "2026-03-22T12:43:38.154612"
  }
}